core/__init__.py
core/finance/__init__.py
core/finance/financial_metrics.py
core/finance/metrics/__init__.py
core/finance/metrics/approved_funds.py
core/finance/metrics/common_items_ratio.py
core/finance/metrics/item_prices.py
core/finance/metrics/new_providers.py
core/finance/metrics/number_of_items.py
core/finance/metrics/proponent_projects.py
core/finance/metrics/raised_funds.py
core/finance/metrics/total_receipts.py
core/finance/metrics/verified_funds.py
core/utils/__init__.py
core/utils/get_project_info_from_pronac.py
core/utils/read_csv.py
salic_ml_dev-0.0.11.dist-info/METADATA
salic_ml_dev-0.0.11.dist-info/RECORD
salic_ml_dev-0.0.11.dist-info/WHEEL
salic_ml_dev-0.0.11.dist-info/top_level.txt
salicml/__init__.py
salicml/models/__init__.py
salicml/models/project_items.py
salicml/models/projects.py
salicml/outliers/__init__.py
salicml/outliers/gaussian_outlier.py
salicml/utils/__init__.py
salicml/utils/csver.py
salicml/utils/dates.py
salicml/utils/plotter.py
salicml/utils/read_csv.py
salicml/utils/utils.py
