Metadata-Version: 2.1
Name: salic-ml-dev
Version: 0.0.11
Summary: Automate the Salic proposal admission process
Home-page: https://github.com/lappis-unb/salic-ml
License: GPL v3.0
Platform: UNKNOWN
Requires-Python: >=3
Requires-Dist: click
Requires-Dist: jupyter
Requires-Dist: matplotlib
Requires-Dist: numpy
Requires-Dist: pandas
Requires-Dist: requests
Requires-Dist: scikit-learn
Requires-Dist: scipy
